gpuutils/GpuUtils.py
gpuutils/__init__.py
gpuutils-0.0.2.dist-info/LICENSE
gpuutils-0.0.2.dist-info/METADATA
gpuutils-0.0.2.dist-info/WHEEL
gpuutils-0.0.2.dist-info/top_level.txt
gpuutils-0.0.2.dist-info/RECORD
