Metadata-Version: 2.1
Name: gpuutils
Version: 0.0.2
Summary: Gpu Utils: Simple Tool for GPU Analysis and Allocation
Home-page: https://github.com/serengil/gpuutils
Author: Sefik Ilkin Serengil
Author-email: serengil@gmail.com
License: UNKNOWN
Platform: UNKNOWN
Classifier: Programming Language :: Python :: 3
Classifier: License :: OSI Approved :: MIT License
Classifier: Operating System :: OS Independent
Requires-Python: >=3.5.5
Requires-Dist: pandas (>=0.23.4)
